cra/__init__.py
cra/air_sounding.py
cra/files.py
cra/layers.py
cra/variables.py
cra-1.1.4.dist-info/LICENSE
cra-1.1.4.dist-info/METADATA
cra-1.1.4.dist-info/WHEEL
cra-1.1.4.dist-info/top_level.txt
cra-1.1.4.dist-info/RECORD
